django_site_variables/__init__.py
django_site_variables/admin.py
django_site_variables/apps.py
django_site_variables/forms.py
django_site_variables/helper.py
django_site_variables/models.py
django_site_variables/tests.py
django_site_variables/migrations/0001_initial.py
django_site_variables/migrations/0002_auto_20211114_1816.py
django_site_variables/migrations/__init__.py
django_site_variables-0.1.dist-info/METADATA
django_site_variables-0.1.dist-info/WHEEL
django_site_variables-0.1.dist-info/top_level.txt
django_site_variables-0.1.dist-info/RECORD
