Metadata-Version: 2.1
Name: django-site-variables
Version: 0.1
Summary: Site variables application
Home-page: UNKNOWN
Author: Mikhail Badrazhan
Author-email: svne@devilweb.ru
License: MIT
Platform: UNKNOWN
Classifier: Programming Language :: Python :: 3
Classifier: License :: OSI Approved :: MIT License
Requires-Python: >=3.6
Requires-Dist: django
